{
  "58625216057": {
    "balance": 400,
    "loan": {
      "exp": 50000,
      "inc": 1000000,
      "credit score": 760,
      "reason:": "SDFSD",
      "job": "FDSFDF",
      "interest": 36000.0,
      "total amount": 86000.0,
      "rate": 0.03
    }
  },
  "48799822329": {
    "balance": 0
  },
  "80999974404": {
    "balance": 0
  },
  "60815913670": {
    "balance": 0
  },
  "26898661417": {
    "balance": 0
  },
  "73918222721": {
    "balance": 0
  },
  "56790311881": {
    "balance": 277
  },
  "35834643982": {
    "balance": 13932
  },
  "34160642536": {
    "balance": 1000
  }
}